Metadata-Version: 1.0
Name: simper-spider
Version: 0.1.0
Summary: This is a simper spider framework
Home-page: https://github.com/BUGLAN/simspider
Author: buglan
Author-email: 1831353087@qq.com
License: UNKNOWN
Platform: UNKNOWN
